aipkg/AI_Notes.docx
aipkg/AI_notes_text.txt
aipkg/__init__.py
aipkg/codepack.py
aipkg/constraint.py
aipkg/knowledgeknights.py
aipkg/logic.py
aipkg/lppexamples.py
aipkg/optimization.py
aipkg/searches.py
aipkg/searches_av.py
aipkg/tictactoe.py
aipkg-0.3.dist-info/METADATA
aipkg-0.3.dist-info/WHEEL
aipkg-0.3.dist-info/licenses/LICENSE
aipkg-0.3.dist-info/RECORD
